mmdict/__init__.py
mmdict/caseless.py
mmdict/errors.py
mmdict/multidict.py
mmdict-0.0.1.dist-info/METADATA
mmdict-0.0.1.dist-info/WHEEL
mmdict-0.0.1.dist-info/top_level.txt
mmdict-0.0.1.dist-info/RECORD
