Metadata-Version: 2.1
Name: mmdict
Version: 0.0.1
Summary: A dictionary-like class that allows keys to have multiple names.
Home-page: UNKNOWN
License: UNKNOWN
Platform: UNKNOWN
Requires-Python: >=3.6
